AUTHORS.rst
CONTRIBUTING.rst
HISTORY.rst
LICENSE
MANIFEST.in
README.rst
setup.cfg
setup.py
FHanalyze/__init__.py
FHanalyze/analyze.py
FHanalyze/error_handling.py
FHanalyze.egg-info/PKG-INFO
FHanalyze.egg-info/SOURCES.txt
FHanalyze.egg-info/dependency_links.txt
FHanalyze.egg-info/entry_points.txt
FHanalyze.egg-info/not-zip-safe
FHanalyze.egg-info/requires.txt
FHanalyze.egg-info/top_level.txt
docs/FHanalyze.rst
docs/Makefile
docs/authors.rst
docs/conf.py
docs/contributing.rst
docs/history.rst
docs/index.rst
docs/installation.rst
docs/make.bat
docs/modules.rst
docs/readme.rst
docs/usage.rst
docs/_build/html/_static/file.png
docs/_build/html/_static/minus.png
docs/_build/html/_static/plus.png
tests/__init__.py
tests/test_analyze.py