Metadata-Version: 1.2
Name: FHanalyze
Version: 0.0.1
Summary: Analyze power readings provided by the FHmonitor package.
Home-page: https://github.com/bitknitting/FHanalyze
Author: Margaret Johnson
Author-email: happyday.mjohnson@gmail.com
License: MIT license
Keywords: FHanalyze
Platform: UNKNOWN
Classifier: Development Status :: 2 - Pre-Alpha
Classifier: Intended Audience :: Developers
Classifier: License :: OSI Approved :: MIT License
Classifier: Natural Language :: English
Classifier: Programming Language :: Python :: 3
Classifier: Programming Language :: Python :: 3.5
Classifier: Programming Language :: Python :: 3.6
Classifier: Programming Language :: Python :: 3.7
Classifier: Programming Language :: Python :: 3.8
Requires-Python: >=3.5
